{"fields":[{"fieldData":"000000000000000000000000000000000000000000000000000000000000000000000000000000","shadowData":["0","0","0","0","0","0","0","0","0","0","0","0","0","0","0","0","0","0","0","B","0","0","0","0","0","B","R","0","0","0","0","R","R","0","0","0","B","R","Y","0","0","0","G","R","B","0","0","0","R","B","R","0","0","R","R","R","Y","B","0","G","G","G","R","G","Y","G","R","B","B","Y","R","R","R","R","B","Y","Y","R"],"cursorData":"000000000000000000000000000000000000000000000000000000000000000000000000000000","arrowData":"000000000000000000000000000000000000000000000000000000000000000000000000000000","autoDrop":false,"puyoPair":"00","advanceNext":true,"slideText":"...!"},{"fieldData":["0","0","0","0","0","0","0","0","0","0","0","0","0","0","0","0","0","0","0","0","0","0","0","0","0","0","0","0","0","0","0","0","0","0","0","0","0","0","0","0","0","0","0","0","0","0","0","0","0","0","0","0","0","0","0","0","0","0","0","0","0","0","0","0","0","0","0","0","0","0","0","0","0","0","0","0","0","0"],"fieldOriginal":["0","0","0","0","0","0","0","0","0","0","0","0","0","0","0","0","0","0","0","0","0","0","0","0","0","0","0","0","0","0","0","0","0","0","0","0","0","0","0","0","0","0","0","0","0","0","0","0","0","0","0","0","0","0","0","0","0","0","0","0","0","0","0","0","0","0","0","0","0","0","0","0","0","0","0","0","0","0"],"shadowData":["0","0","0","0","0","0","0","0","0","0","0","0","0","0","0","0","0","0","0","B","0","0","0","0","0","B","R","0","0","0","0","R","R","0","0","0","B","R","Y","0","0","0","G","R","B","0","0","0","R","B","R","0","0","R","R","R","Y","B","0","G","G","G","R","G","Y","G","R","B","B","Y","R","R","R","R","B","Y","Y","R"],"cursorData":"000000000000000000000000000000000000000000000000000000000000000000000000000000","arrowData":"000000000000000000000000000000000000000000000000000000000000000000000000000000","slideText":"...!","autoDrop":true,"advanceNext":true,"puyoPair":"RR"},{"fieldData":["0","0","0","0","0","0","0","0","0","0","0","0","0","0","0","0","0","0","0","0","0","0","0","0","0","0","0","0","0","0","0","0","0","0","0","0","0","0","0","0","0","0","0","0","0","0","0","0","0","0","0","0","0","0","0","0","0","0","0","0","0","0","0","0","0","0","R","0","0","0","0","0","R","0","0","0","0","0"],"fieldOriginal":["0","0","0","0","0","0","0","0","0","0","0","0","0","0","0","0","0","0","0","0","0","0","0","0","0","0","0","0","0","0","0","0","0","0","0","0","0","0","0","0","0","0","0","0","0","0","0","0","0","0","0","0","0","0","0","0","0","0","0","0","0","0","0","0","0","0","R","0","0","0","0","0","R","0","0","0","0","0"],"shadowData":["0","0","0","0","0","0","0","0","0","0","0","0","0","0","0","0","0","0","0","B","0","0","0","0","0","B","R","0","0","0","0","R","R","0","0","0","B","R","Y","0","0","0","G","R","B","0","0","0","R","B","R","0","0","R","R","R","Y","B","0","G","G","G","R","G","Y","G","R","B","B","Y","R","R","R","R","B","Y","Y","R"],"cursorData":"000000000000000000000000000000000000000000000000000000000000000000000000000000","arrowData":"000000000000000000000000000000000000000000000000000000000000000000000000000000","slideText":"...!","autoDrop":true,"advanceNext":true,"puyoPair":"BR"},{"fieldData":["0","0","0","0","0","0","0","0","0","0","0","0","0","0","0","0","0","0","0","0","0","0","0","0","0","0","0","0","0","0","0","0","0","0","0","0","0","0","0","0","0","0","0","0","0","0","0","0","0","0","0","0","0","0","0","0","0","0","0","0","0","0","0","0","0","0","R","0","0","0","0","0","R","R","B","0","0","0"],"fieldOriginal":["0","0","0","0","0","0","0","0","0","0","0","0","0","0","0","0","0","0","0","0","0","0","0","0","0","0","0","0","0","0","0","0","0","0","0","0","0","0","0","0","0","0","0","0","0","0","0","0","0","0","0","0","0","0","0","0","0","0","0","0","0","0","0","0","0","0","R","0","0","0","0","0","R","R","B","0","0","0"],"shadowData":["0","0","0","0","0","0","0","0","0","0","0","0","0","0","0","0","0","0","0","B","0","0","0","0","0","B","R","0","0","0","0","R","R","0","0","0","B","R","Y","0","0","0","G","R","B","0","0","0","R","B","R","0","0","R","R","R","Y","B","0","G","G","G","R","G","Y","G","R","B","B","Y","R","R","R","R","B","Y","Y","R"],"cursorData":"000000000000000000000000000000000000000000000000000000000000000000000000000000","arrowData":"000000000000000000000000000000000000000000000000000000000000000000000000000000","slideText":"...!","autoDrop":true,"advanceNext":true,"puyoPair":"BY"},{"fieldData":["0","0","0","0","0","0","0","0","0","0","0","0","0","0","0","0","0","0","0","0","0","0","0","0","0","0","0","0","0","0","0","0","0","0","0","0","0","0","0","0","0","0","0","0","0","0","0","0","0","0","0","0","0","0","0","0","0","0","0","0","0","0","0","0","0","0","R","0","B","0","0","0","R","R","B","Y","0","0"],"fieldOriginal":["0","0","0","0","0","0","0","0","0","0","0","0","0","0","0","0","0","0","0","0","0","0","0","0","0","0","0","0","0","0","0","0","0","0","0","0","0","0","0","0","0","0","0","0","0","0","0","0","0","0","0","0","0","0","0","0","0","0","0","0","0","0","0","0","0","0","R","0","B","0","0","0","R","R","B","Y","0","0"],"shadowData":["0","0","0","0","0","0","0","0","0","0","0","0","0","0","0","0","0","0","0","B","0","0","0","0","0","B","R","0","0","0","0","R","R","0","0","0","B","R","Y","0","0","0","G","R","B","0","0","0","R","B","R","0","0","R","R","R","Y","B","0","G","G","G","R","G","Y","G","R","B","B","Y","R","R","R","R","B","Y","Y","R"],"cursorData":"000000000000000000000000000000000000000000000000000000000000000000000000000000","arrowData":"000000000000000000000000000000000000000000000000000000000000000000000000000000","slideText":"...!","autoDrop":true,"advanceNext":true,"puyoPair":"RY"},{"fieldData":["0","0","0","0","0","0","0","0","0","0","0","0","0","0","0","0","0","0","0","0","0","0","0","0","0","0","0","0","0","0","0","0","0","0","0","0","0","0","0","0","0","0","0","0","0","0","0","0","0","0","0","0","0","0","0","0","0","0","0","0","0","0","0","0","0","0","R","0","B","0","0","0","R","R","B","Y","Y","R"],"fieldOriginal":["0","0","0","0","0","0","0","0","0","0","0","0","0","0","0","0","0","0","0","0","0","0","0","0","0","0","0","0","0","0","0","0","0","0","0","0","0","0","0","0","0","0","0","0","0","0","0","0","0","0","0","0","0","0","0","0","0","0","0","0","0","0","0","0","0","0","R","0","B","0","0","0","R","R","B","Y","Y","R"],"shadowData":["0","0","0","0","0","0","0","0","0","0","0","0","0","0","0","0","0","0","0","B","0","0","0","0","0","B","R","0","0","0","0","R","R","0","0","0","B","R","Y","0","0","0","G","R","B","0","0","0","R","B","R","0","0","R","R","R","Y","B","0","G","G","G","R","G","Y","G","R","B","B","Y","R","R","R","R","B","Y","Y","R"],"cursorData":"000000000000000000000000000000000000000000000000000000000000000000000000000000","arrowData":"000000000000000000000000000000000000000000000000000000000000000000000000000000","slideText":"...!","autoDrop":true,"advanceNext":true,"puyoPair":"YG"},{"fieldData":["0","0","0","0","0","0","0","0","0","0","0","0","0","0","0","0","0","0","0","0","0","0","0","0","0","0","0","0","0","0","0","0","0","0","0","0","0","0","0","0","0","0","0","0","0","0","0","0","0","0","0","0","0","0","0","0","0","0","0","0","0","0","0","G","0","0","R","0","B","Y","0","0","R","R","B","Y","Y","R"],"fieldOriginal":["0","0","0","0","0","0","0","0","0","0","0","0","0","0","0","0","0","0","0","0","0","0","0","0","0","0","0","0","0","0","0","0","0","0","0","0","0","0","0","0","0","0","0","0","0","0","0","0","0","0","0","0","0","0","0","0","0","0","0","0","0","0","0","G","0","0","R","0","B","Y","0","0","R","R","B","Y","Y","R"],"shadowData":["0","0","0","0","0","0","0","0","0","0","0","0","0","0","0","0","0","0","0","B","0","0","0","0","0","B","R","0","0","0","0","R","R","0","0","0","B","R","Y","0","0","0","G","R","B","0","0","0","R","B","R","0","0","R","R","R","Y","B","0","G","G","G","R","G","Y","G","R","B","B","Y","R","R","R","R","B","Y","Y","R"],"cursorData":"000000000000000000000000000000000000000000000000000000000000000000000000000000","arrowData":"000000000000000000000000000000000000000000000000000000000000000000000000000000","slideText":"...!","autoDrop":true,"advanceNext":true,"puyoPair":"RR"},{"fieldData":["0","0","0","0","0","0","0","0","0","0","0","0","0","0","0","0","0","0","0","0","0","0","0","0","0","0","0","0","0","0","0","0","0","0","0","0","0","0","0","0","0","0","0","0","0","0","0","0","0","0","0","0","0","0","0","0","0","0","0","0","0","0","0","G","0","0","R","0","B","Y","R","R","R","R","B","Y","Y","R"],"fieldOriginal":["0","0","0","0","0","0","0","0","0","0","0","0","0","0","0","0","0","0","0","0","0","0","0","0","0","0","0","0","0","0","0","0","0","0","0","0","0","0","0","0","0","0","0","0","0","0","0","0","0","0","0","0","0","0","0","0","0","0","0","0","0","0","0","G","0","0","R","0","B","Y","R","R","R","R","B","Y","Y","R"],"shadowData":["0","0","0","0","0","0","0","0","0","0","0","0","0","0","0","0","0","0","0","B","0","0","0","0","0","B","R","0","0","0","0","R","R","0","0","0","B","R","Y","0","0","0","G","R","B","0","0","0","R","B","R","0","0","R","R","R","Y","B","0","G","G","G","R","G","Y","G","R","B","B","Y","R","R","R","R","B","Y","Y","R"],"cursorData":"000000000000000000000000000000000000000000000000000000000000000000000000000000","arrowData":"000000000000000000000000000000000000000000000000000000000000000000000000000000","slideText":"...!","autoDrop":true,"advanceNext":true,"puyoPair":"BG"},{"fieldData":["0","0","0","0","0","0","0","0","0","0","0","0","0","0","0","0","0","0","0","0","0","0","0","0","0","0","0","0","0","0","0","0","0","0","0","0","0","0","0","0","0","0","0","0","0","0","0","0","0","0","0","0","0","0","0","0","0","0","0","0","G","0","0","G","0","0","R","B","B","Y","R","R","R","R","B","Y","Y","R"],"fieldOriginal":["0","0","0","0","0","0","0","0","0","0","0","0","0","0","0","0","0","0","0","0","0","0","0","0","0","0","0","0","0","0","0","0","0","0","0","0","0","0","0","0","0","0","0","0","0","0","0","0","0","0","0","0","0","0","0","0","0","0","0","0","G","0","0","G","0","0","R","B","B","Y","R","R","R","R","B","Y","Y","R"],"shadowData":["0","0","0","0","0","0","0","0","0","0","0","0","0","0","0","0","0","0","0","B","0","0","0","0","0","B","R","0","0","0","0","R","R","0","0","0","B","R","Y","0","0","0","G","R","B","0","0","0","R","B","R","0","0","R","R","R","Y","B","0","G","G","G","R","G","Y","G","R","B","B","Y","R","R","R","R","B","Y","Y","R"],"cursorData":"000000000000000000000000000000000000000000000000000000000000000000000000000000","arrowData":"000000000000000000000000000000000000000000000000000000000000000000000000000000","slideText":"...!","autoDrop":true,"advanceNext":true,"puyoPair":"BR"},{"fieldData":["0","0","0","0","0","0","0","0","0","0","0","0","0","0","0","0","0","0","0","0","0","0","0","0","0","0","0","0","0","0","0","0","0","0","0","0","0","0","0","0","0","0","0","0","0","0","0","0","0","0","0","0","0","0","0","0","0","B","0","0","G","0","R","G","0","0","R","B","B","Y","R","R","R","R","B","Y","Y","R"],"fieldOriginal":["0","0","0","0","0","0","0","0","0","0","0","0","0","0","0","0","0","0","0","0","0","0","0","0","0","0","0","0","0","0","0","0","0","0","0","0","0","0","0","0","0","0","0","0","0","0","0","0","0","0","0","0","0","0","0","0","0","B","0","0","G","0","R","G","0","0","R","B","B","Y","R","R","R","R","B","Y","Y","R"],"shadowData":["0","0","0","0","0","0","0","0","0","0","0","0","0","0","0","0","0","0","0","B","0","0","0","0","0","B","R","0","0","0","0","R","R","0","0","0","B","R","Y","0","0","0","G","R","B","0","0","0","R","B","R","0","0","R","R","R","Y","B","0","G","G","G","R","G","Y","G","R","B","B","Y","R","R","R","R","B","Y","Y","R"],"cursorData":"000000000000000000000000000000000000000000000000000000000000000000000000000000","arrowData":"000000000000000000000000000000000000000000000000000000000000000000000000000000","slideText":"...!","autoDrop":true,"advanceNext":true,"puyoPair":"RG"},{"fieldData":["0","0","0","0","0","0","0","0","0","0","0","0","0","0","0","0","0","0","0","0","0","0","0","0","0","0","0","0","0","0","0","0","0","0","0","0","0","0","0","0","0","0","0","0","0","0","0","0","0","0","0","0","0","0","0","R","0","B","0","0","G","G","R","G","0","0","R","B","B","Y","R","R","R","R","B","Y","Y","R"],"fieldOriginal":["0","0","0","0","0","0","0","0","0","0","0","0","0","0","0","0","0","0","0","0","0","0","0","0","0","0","0","0","0","0","0","0","0","0","0","0","0","0","0","0","0","0","0","0","0","0","0","0","0","0","0","0","0","0","0","R","0","B","0","0","G","G","R","G","0","0","R","B","B","Y","R","R","R","R","B","Y","Y","R"],"shadowData":["0","0","0","0","0","0","0","0","0","0","0","0","0","0","0","0","0","0","0","B","0","0","0","0","0","B","R","0","0","0","0","R","R","0","0","0","B","R","Y","0","0","0","G","R","B","0","0","0","R","B","R","0","0","R","R","R","Y","B","0","G","G","G","R","G","Y","G","R","B","B","Y","R","R","R","R","B","Y","Y","R"],"cursorData":"000000000000000000000000000000000000000000000000000000000000000000000000000000","arrowData":"000000000000000000000000000000000000000000000000000000000000000000000000000000","slideText":"...!","autoDrop":true,"advanceNext":true,"puyoPair":"RB"},{"fieldData":["0","0","0","0","0","0","0","0","0","0","0","0","0","0","0","0","0","0","0","0","0","0","0","0","0","0","0","0","0","0","0","0","0","0","0","0","0","0","0","0","0","0","0","0","0","0","0","0","0","B","0","0","0","0","R","R","0","B","0","0","G","G","R","G","0","0","R","B","B","Y","R","R","R","R","B","Y","Y","R"],"fieldOriginal":["0","0","0","0","0","0","0","0","0","0","0","0","0","0","0","0","0","0","0","0","0","0","0","0","0","0","0","0","0","0","0","0","0","0","0","0","0","0","0","0","0","0","0","0","0","0","0","0","0","B","0","0","0","0","R","R","0","B","0","0","G","G","R","G","0","0","R","B","B","Y","R","R","R","R","B","Y","Y","R"],"shadowData":["0","0","0","0","0","0","0","0","0","0","0","0","0","0","0","0","0","0","0","B","0","0","0","0","0","B","R","0","0","0","0","R","R","0","0","0","B","R","Y","0","0","0","G","R","B","0","0","0","R","B","R","0","0","R","R","R","Y","B","0","G","G","G","R","G","Y","G","R","B","B","Y","R","R","R","R","B","Y","Y","R"],"cursorData":"000000000000000000000000000000000000000000000000000000000000000000000000000000","arrowData":"000000000000000000000000000000000000000000000000000000000000000000000000000000","slideText":"...!","autoDrop":true,"advanceNext":true,"puyoPair":"YG"},{"fieldData":["0","0","0","0","0","0","0","0","0","0","0","0","0","0","0","0","0","0","0","0","0","0","0","0","0","0","0","0","0","0","0","0","0","0","0","0","0","0","0","0","0","0","0","0","0","0","0","0","0","B","0","0","0","0","R","R","0","B","0","0","G","G","R","G","Y","G","R","B","B","Y","R","R","R","R","B","Y","Y","R"],"fieldOriginal":["0","0","0","0","0","0","0","0","0","0","0","0","0","0","0","0","0","0","0","0","0","0","0","0","0","0","0","0","0","0","0","0","0","0","0","0","0","0","0","0","0","0","0","0","0","0","0","0","0","B","0","0","0","0","R","R","0","B","0","0","G","G","R","G","Y","G","R","B","B","Y","R","R","R","R","B","Y","Y","R"],"shadowData":["0","0","0","0","0","0","0","0","0","0","0","0","0","0","0","0","0","0","0","B","0","0","0","0","0","B","R","0","0","0","0","R","R","0","0","0","B","R","Y","0","0","0","G","R","B","0","0","0","R","B","R","0","0","R","R","R","Y","B","0","G","G","G","R","G","Y","G","R","B","B","Y","R","R","R","R","B","Y","Y","R"],"cursorData":"000000000000000000000000000000000000000000000000000000000000000000000000000000","arrowData":"000000000000000000000000000000000000000000000000000000000000000000000000000000","slideText":"...!","autoDrop":true,"advanceNext":true,"puyoPair":"GR"},{"fieldData":["0","0","0","0","0","0","0","0","0","0","0","0","0","0","0","0","0","0","0","0","0","0","0","0","0","0","0","0","0","0","0","0","0","0","0","0","0","0","0","0","0","0","0","0","0","0","0","0","0","B","0","0","0","R","R","R","0","B","0","G","G","G","R","G","Y","G","R","B","B","Y","R","R","R","R","B","Y","Y","R"],"fieldOriginal":["0","0","0","0","0","0","0","0","0","0","0","0","0","0","0","0","0","0","0","0","0","0","0","0","0","0","0","0","0","0","0","0","0","0","0","0","0","0","0","0","0","0","0","0","0","0","0","0","0","B","0","0","0","R","R","R","0","B","0","G","G","G","R","G","Y","G","R","B","B","Y","R","R","R","R","B","Y","Y","R"],"shadowData":["0","0","0","0","0","0","0","0","0","0","0","0","0","0","0","0","0","0","0","B","0","0","0","0","0","B","R","0","0","0","0","R","R","0","0","0","B","R","Y","0","0","0","G","R","B","0","0","0","R","B","R","0","0","R","R","R","Y","B","0","G","G","G","R","G","Y","G","R","B","B","Y","R","R","R","R","B","Y","Y","R"],"cursorData":"000000000000000000000000000000000000000000000000000000000000000000000000000000","arrowData":"000000000000000000000000000000000000000000000000000000000000000000000000000000","slideText":"...!","autoDrop":true,"advanceNext":true,"puyoPair":"RR"},{"fieldData":["0","0","0","0","0","0","0","0","0","0","0","0","0","0","0","0","0","0","0","0","0","0","0","0","0","0","0","0","0","0","0","0","0","0","0","0","0","0","0","0","0","0","0","R","0","0","0","0","R","B","0","0","0","R","R","R","0","B","0","G","G","G","R","G","Y","G","R","B","B","Y","R","R","R","R","B","Y","Y","R"],"fieldOriginal":["0","0","0","0","0","0","0","0","0","0","0","0","0","0","0","0","0","0","0","0","0","0","0","0","0","0","0","0","0","0","0","0","0","0","0","0","0","0","0","0","0","0","0","R","0","0","0","0","R","B","0","0","0","R","R","R","0","B","0","G","G","G","R","G","Y","G","R","B","B","Y","R","R","R","R","B","Y","Y","R"],"shadowData":["0","0","0","0","0","0","0","0","0","0","0","0","0","0","0","0","0","0","0","B","0","0","0","0","0","B","R","0","0","0","0","R","R","0","0","0","B","R","Y","0","0","0","G","R","B","0","0","0","R","B","R","0","0","R","R","R","Y","B","0","G","G","G","R","G","Y","G","R","B","B","Y","R","R","R","R","B","Y","Y","R"],"cursorData":"000000000000000000000000000000000000000000000000000000000000000000000000000000","arrowData":"000000000000000000000000000000000000000000000000000000000000000000000000000000","slideText":"...!","autoDrop":true,"advanceNext":true,"puyoPair":"YR"},{"fieldData":["0","0","0","0","0","0","0","0","0","0","0","0","0","0","0","0","0","0","0","0","0","0","0","0","0","0","0","0","0","0","0","0","0","0","0","0","0","0","0","0","0","0","0","R","0","0","0","0","R","B","R","0","0","R","R","R","Y","B","0","G","G","G","R","G","Y","G","R","B","B","Y","R","R","R","R","B","Y","Y","R"],"fieldOriginal":["0","0","0","0","0","0","0","0","0","0","0","0","0","0","0","0","0","0","0","0","0","0","0","0","0","0","0","0","0","0","0","0","0","0","0","0","0","0","0","0","0","0","0","R","0","0","0","0","R","B","R","0","0","R","R","R","Y","B","0","G","G","G","R","G","Y","G","R","B","B","Y","R","R","R","R","B","Y","Y","R"],"shadowData":["0","0","0","0","0","0","0","0","0","0","0","0","0","0","0","0","0","0","0","B","0","0","0","0","0","B","R","0","0","0","0","R","R","0","0","0","B","R","Y","0","0","0","G","R","B","0","0","0","R","B","R","0","0","R","R","R","Y","B","0","G","G","G","R","G","Y","G","R","B","B","Y","R","R","R","R","B","Y","Y","R"],"cursorData":"000000000000000000000000000000000000000000000000000000000000000000000000000000","arrowData":"000000000000000000000000000000000000000000000000000000000000000000000000000000","slideText":"...!","autoDrop":true,"advanceNext":true,"puyoPair":"RR"},{"fieldData":["0","0","0","0","0","0","0","0","0","0","0","0","0","0","0","0","0","0","0","0","0","0","0","0","0","0","0","0","0","0","0","R","0","0","0","0","0","R","0","0","0","0","0","R","0","0","0","0","R","B","R","0","0","R","R","R","Y","B","0","G","G","G","R","G","Y","G","R","B","B","Y","R","R","R","R","B","Y","Y","R"],"fieldOriginal":["0","0","0","0","0","0","0","0","0","0","0","0","0","0","0","0","0","0","0","0","0","0","0","0","0","0","0","0","0","0","0","R","0","0","0","0","0","R","0","0","0","0","0","R","0","0","0","0","R","B","R","0","0","R","R","R","Y","B","0","G","G","G","R","G","Y","G","R","B","B","Y","R","R","R","R","B","Y","Y","R"],"shadowData":["0","0","0","0","0","0","0","0","0","0","0","0","0","0","0","0","0","0","0","B","0","0","0","0","0","B","R","0","0","0","0","R","R","0","0","0","B","R","Y","0","0","0","G","R","B","0","0","0","R","B","R","0","0","R","R","R","Y","B","0","G","G","G","R","G","Y","G","R","B","B","Y","R","R","R","R","B","Y","Y","R"],"cursorData":"000000000000000000000000000000000000000000000000000000000000000000000000000000","arrowData":"000000000000000000000000000000000000000000000000000000000000000000000000000000","slideText":"...!","autoDrop":true,"advanceNext":true,"puyoPair":"BY"},{"fieldData":["0","0","0","0","0","0","0","0","0","0","0","0","0","0","0","0","0","0","0","0","0","0","0","0","0","0","0","0","0","0","0","R","0","0","0","0","0","R","Y","0","0","0","0","R","B","0","0","0","R","B","R","0","0","R","R","R","Y","B","0","G","G","G","R","G","Y","G","R","B","B","Y","R","R","R","R","B","Y","Y","R"],"fieldOriginal":["0","0","0","0","0","0","0","0","0","0","0","0","0","0","0","0","0","0","0","0","0","0","0","0","0","0","0","0","0","0","0","R","0","0","0","0","0","R","Y","0","0","0","0","R","B","0","0","0","R","B","R","0","0","R","R","R","Y","B","0","G","G","G","R","G","Y","G","R","B","B","Y","R","R","R","R","B","Y","Y","R"],"shadowData":["0","0","0","0","0","0","0","0","0","0","0","0","0","0","0","0","0","0","0","B","0","0","0","0","0","B","R","0","0","0","0","R","R","0","0","0","B","R","Y","0","0","0","G","R","B","0","0","0","R","B","R","0","0","R","R","R","Y","B","0","G","G","G","R","G","Y","G","R","B","B","Y","R","R","R","R","B","Y","Y","R"],"cursorData":"000000000000000000000000000000000000000000000000000000000000000000000000000000","arrowData":"000000000000000000000000000000000000000000000000000000000000000000000000000000","slideText":"...!","autoDrop":true,"advanceNext":true,"puyoPair":"BG"},{"fieldData":["0","0","0","0","0","0","0","0","0","0","0","0","0","0","0","0","0","0","0","0","0","0","0","0","0","0","0","0","0","0","0","R","0","0","0","0","B","R","Y","0","0","0","G","R","B","0","0","0","R","B","R","0","0","R","R","R","Y","B","0","G","G","G","R","G","Y","G","R","B","B","Y","R","R","R","R","B","Y","Y","R"],"fieldOriginal":["0","0","0","0","0","0","0","0","0","0","0","0","0","0","0","0","0","0","0","0","0","0","0","0","0","0","0","0","0","0","0","R","0","0","0","0","B","R","Y","0","0","0","G","R","B","0","0","0","R","B","R","0","0","R","R","R","Y","B","0","G","G","G","R","G","Y","G","R","B","B","Y","R","R","R","R","B","Y","Y","R"],"shadowData":["0","0","0","0","0","0","0","0","0","0","0","0","0","0","0","0","0","0","0","B","0","0","0","0","0","B","R","0","0","0","0","R","R","0","0","0","B","R","Y","0","0","0","G","R","B","0","0","0","R","B","R","0","0","R","R","R","Y","B","0","G","G","G","R","G","Y","G","R","B","B","Y","R","R","R","R","B","Y","Y","R"],"cursorData":"000000000000000000000000000000000000000000000000000000000000000000000000000000","arrowData":"000000000000000000000000000000000000000000000000000000000000000000000000000000","slideText":"...!","autoDrop":true,"advanceNext":true,"puyoPair":"BB"},{"fieldData":["0","0","0","0","0","0","0","0","0","0","0","0","0","0","0","0","0","0","0","B","0","0","0","0","0","B","0","0","0","0","0","R","0","0","0","0","B","R","Y","0","0","0","G","R","B","0","0","0","R","B","R","0","0","R","R","R","Y","B","0","G","G","G","R","G","Y","G","R","B","B","Y","R","R","R","R","B","Y","Y","R"],"fieldOriginal":["0","0","0","0","0","0","0","0","0","0","0","0","0","0","0","0","0","0","0","B","0","0","0","0","0","B","0","0","0","0","0","R","0","0","0","0","B","R","Y","0","0","0","G","R","B","0","0","0","R","B","R","0","0","R","R","R","Y","B","0","G","G","G","R","G","Y","G","R","B","B","Y","R","R","R","R","B","Y","Y","R"],"shadowData":["0","0","0","0","0","0","0","0","0","0","0","0","0","0","0","0","0","0","0","B","0","0","0","0","0","B","R","0","0","0","0","R","R","0","0","0","B","R","Y","0","0","0","G","R","B","0","0","0","R","B","R","0","0","R","R","R","Y","B","0","G","G","G","R","G","Y","G","R","B","B","Y","R","R","R","R","B","Y","Y","R"],"cursorData":"000000000000000000000000000000000000000000000000000000000000000000000000000000","arrowData":"000000000000000000000000000000000000000000000000000000000000000000000000000000","slideText":"...!","autoDrop":true,"advanceNext":true,"puyoPair":"RR"},{"fieldData":["0","0","0","0","0","0","0","0","0","0","0","0","0","0","0","0","0","0","0","B","0","0","0","0","0","B","R","0","0","0","0","R","R","0","0","0","B","R","Y","0","0","0","G","R","B","0","0","0","R","B","R","0","0","R","R","R","Y","B","0","G","G","G","R","G","Y","G","R","B","B","Y","R","R","R","R","B","Y","Y","R"],"fieldOriginal":["0","0","0","0","0","0","0","0","0","0","0","0","0","0","0","0","0","0","0","B","0","0","0","0","0","B","R","0","0","0","0","R","R","0","0","0","B","R","Y","0","0","0","G","R","B","0","0","0","R","B","R","0","0","R","R","R","Y","B","0","G","G","G","R","G","Y","G","R","B","B","Y","R","R","R","R","B","Y","Y","R"],"shadowData":["0","0","0","0","0","0","0","0","0","0","0","0","0","0","0","0","0","0","B","0","0","0","0","0","Y","0","0","0","0","0","Y","R","0","0","0","0","G","B","0","0","0","0","G","B","Y","0","0","0","R","Y","R","0","G","R","R","R","Y","B","G","G","G","G","R","G","Y","G","R","B","B","Y","R","R","R","R","B","Y","Y","R"],"cursorData":"000000000000000000000000000000000000000000000000000000000000000000000000000000","arrowData":"000000000000000000000000000000000000000000000000000000000000000000000000000000","slideText":"...!","autoDrop":true,"advanceNext":true,"puyoPair":"YB"},{"fieldData":["0","0","0","0","0","0","0","0","0","0","0","0","0","0","0","0","0","0","0","0","0","0","0","0","0","0","0","0","0","0","0","0","0","0","0","0","0","0","0","0","0","0","G","B","Y","0","0","0","R","Y","R","0","0","R","R","R","Y","B","0","G","G","G","R","G","Y","G","R","B","B","Y","R","R","R","R","B","Y","Y","R"],"fieldOriginal":["0","0","0","0","0","0","0","0","0","0","0","0","0","0","0","0","0","0","0","0","0","0","0","0","0","0","0","0","0","0","0","0","0","0","0","0","0","0","0","0","0","0","G","B","Y","0","0","0","R","Y","R","0","0","R","R","R","Y","B","0","G","G","G","R","G","Y","G","R","B","B","Y","R","R","R","R","B","Y","Y","R"],"shadowData":["0","0","0","0","0","0","0","0","0","0","0","0","0","0","0","0","0","0","B","0","0","0","0","0","Y","0","0","0","0","0","Y","R","0","0","0","0","G","B","0","0","0","0","G","B","Y","0","0","0","R","Y","R","0","G","R","R","R","Y","B","G","G","G","G","R","G","Y","G","R","B","B","Y","R","R","R","R","B","Y","Y","R"],"cursorData":"000000000000000000000000000000000000000000000000000000000000000000000000000000","arrowData":"000000000000000000000000000000000000000000000000000000000000000000000000000000","slideText":"...!","autoDrop":true,"advanceNext":true,"puyoPair":"BG"},{"fieldData":["0","0","0","0","0","0","0","0","0","0","0","0","0","0","0","0","0","0","0","0","0","0","0","0","0","0","0","0","0","0","0","0","0","0","0","0","G","B","0","0","0","0","G","B","Y","0","0","0","R","Y","R","0","0","R","R","R","Y","B","0","G","G","G","R","G","Y","G","R","B","B","Y","R","R","R","R","B","Y","Y","R"],"fieldOriginal":["0","0","0","0","0","0","0","0","0","0","0","0","0","0","0","0","0","0","0","0","0","0","0","0","0","0","0","0","0","0","0","0","0","0","0","0","G","B","0","0","0","0","G","B","Y","0","0","0","R","Y","R","0","0","R","R","R","Y","B","0","G","G","G","R","G","Y","G","R","B","B","Y","R","R","R","R","B","Y","Y","R"],"shadowData":["0","0","0","0","0","0","0","0","0","0","0","0","0","0","0","0","0","0","B","0","0","0","0","0","Y","0","0","0","0","0","Y","R","0","0","0","0","G","B","0","0","0","0","G","B","Y","0","0","0","R","Y","R","0","G","R","R","R","Y","B","G","G","G","G","R","G","Y","G","R","B","B","Y","R","R","R","R","B","Y","Y","R"],"cursorData":"000000000000000000000000000000000000000000000000000000000000000000000000000000","arrowData":"000000000000000000000000000000000000000000000000000000000000000000000000000000","slideText":"...!","autoDrop":true,"advanceNext":true,"puyoPair":"YR"},{"fieldData":["0","0","0","0","0","0","0","0","0","0","0","0","0","0","0","0","0","0","0","0","0","0","0","0","0","0","0","0","0","0","Y","R","0","0","0","0","G","B","0","0","0","0","G","B","Y","0","0","0","R","Y","R","0","0","R","R","R","Y","B","0","G","G","G","R","G","Y","G","R","B","B","Y","R","R","R","R","B","Y","Y","R"],"fieldOriginal":["0","0","0","0","0","0","0","0","0","0","0","0","0","0","0","0","0","0","0","0","0","0","0","0","0","0","0","0","0","0","Y","R","0","0","0","0","G","B","0","0","0","0","G","B","Y","0","0","0","R","Y","R","0","0","R","R","R","Y","B","0","G","G","G","R","G","Y","G","R","B","B","Y","R","R","R","R","B","Y","Y","R"],"shadowData":["0","0","0","0","0","0","0","0","0","0","0","0","0","0","0","0","0","0","B","0","0","0","0","0","Y","0","0","0","0","0","Y","R","0","0","0","0","G","B","0","0","0","0","G","B","Y","0","0","0","R","Y","R","0","G","R","R","R","Y","B","G","G","G","G","R","G","Y","G","R","B","B","Y","R","R","R","R","B","Y","Y","R"],"cursorData":"000000000000000000000000000000000000000000000000000000000000000000000000000000","arrowData":"000000000000000000000000000000000000000000000000000000000000000000000000000000","slideText":"...!","autoDrop":true,"advanceNext":true,"puyoPair":"BY"},{"fieldData":["0","0","0","0","0","0","0","0","0","0","0","0","0","0","0","0","0","0","B","0","0","0","0","0","Y","0","0","0","0","0","Y","R","0","0","0","0","G","B","0","0","0","0","G","B","Y","0","0","0","R","Y","R","0","0","R","R","R","Y","B","0","G","G","G","R","G","Y","G","R","B","B","Y","R","R","R","R","B","Y","Y","R"],"fieldOriginal":["0","0","0","0","0","0","0","0","0","0","0","0","0","0","0","0","0","0","B","0","0","0","0","0","Y","0","0","0","0","0","Y","R","0","0","0","0","G","B","0","0","0","0","G","B","Y","0","0","0","R","Y","R","0","0","R","R","R","Y","B","0","G","G","G","R","G","Y","G","R","B","B","Y","R","R","R","R","B","Y","Y","R"],"shadowData":["0","0","0","0","0","0","0","0","0","0","0","0","0","0","0","0","0","0","B","0","0","0","0","0","Y","0","0","0","0","0","Y","R","0","0","0","0","G","B","0","0","0","0","G","B","Y","0","0","0","R","Y","R","0","G","R","R","R","Y","B","G","G","G","G","R","G","Y","G","R","B","B","Y","R","R","R","R","B","Y","Y","R"],"cursorData":"000000000000000000000000000000000000000000000000000000000000000000000000000000","arrowData":"000000000000000000000000000000000000000000000000000000000000000000000000000000","slideText":"...!","autoDrop":true,"advanceNext":true,"puyoPair":"GG"},{"fieldData":["0","0","0","0","0","0","0","0","0","0","0","0","0","0","0","0","0","0","B","0","0","0","0","0","Y","0","0","0","0","0","Y","R","0","0","0","0","G","B","0","0","0","0","G","B","Y","0","0","0","R","Y","R","0","G","R","R","R","Y","B","G","G","G","G","R","G","Y","G","R","B","B","Y","R","R","R","R","B","Y","Y","R"],"fieldOriginal":["0","0","0","0","0","0","0","0","0","0","0","0","0","0","0","0","0","0","B","0","0","0","0","0","Y","0","0","0","0","0","Y","R","0","0","0","0","G","B","0","0","0","0","G","B","Y","0","0","0","R","Y","R","0","G","R","R","R","Y","B","G","G","G","G","R","G","Y","G","R","B","B","Y","R","R","R","R","B","Y","Y","R"],"shadowData":"000000000000000000000000000000000000000000000000000000000000000000000000000000","cursorData":"000000000000000000000000000000000000000000000000000000000000000000000000000000","arrowData":"000000000000000000000000000000000000000000000000000000000000000000000000000000","slideText":"...!","autoDrop":true,"advanceNext":true}],"next":{"seed":52346,"nextQueue":"RRBRBYRYYGRRBGBRRGRBYGGRRRYRRRBYBGBBRRYBBGYRBYGG"}}