{"fields":[{"fieldData":"000000000000000000000000000000000000000000000000000000000000000000000000000000","shadowData":["0","0","0","0","0","0","0","0","0","0","0","0","0","0","0","0","0","0","0","0","0","0","B","0","0","0","0","0","Y","B","0","0","0","0","Y","Y","0","0","0","0","Y","B","0","Y","G","0","B","B","G","G","Y","0","Y","Y","G","Y","B","R","B","R","Y","B","R","B","Y","R","Y","B","R","B","Y","R","Y","B","R","B","Y","G"],"cursorData":"000000000000000000000000000000000000000000000000000000000000000000000000000000","arrowData":"000000000000000000000000000000000000000000000000000000000000000000000000000000","autoDrop":false,"puyoPair":"00","advanceNext":true,"slideText":"Target: 11 Chain"},{"fieldData":["0","0","0","0","0","0","0","0","0","0","0","0","0","0","0","0","0","0","0","0","0","0","0","0","0","0","0","0","0","0","0","0","0","0","0","0","0","0","0","0","0","0","0","0","0","0","0","0","0","0","0","0","0","0","0","0","0","0","0","0","0","0","0","0","0","0","0","0","0","0","0","0","0","0","0","0","0","0"],"fieldOriginal":["0","0","0","0","0","0","0","0","0","0","0","0","0","0","0","0","0","0","0","0","0","0","0","0","0","0","0","0","0","0","0","0","0","0","0","0","0","0","0","0","0","0","0","0","0","0","0","0","0","0","0","0","0","0","0","0","0","0","0","0","0","0","0","0","0","0","0","0","0","0","0","0","0","0","0","0","0","0"],"shadowData":["0","0","0","0","0","0","0","0","0","0","0","0","0","0","0","0","0","0","0","0","0","0","B","0","0","0","0","0","Y","B","0","0","0","0","Y","Y","0","0","0","0","Y","B","0","Y","G","0","B","B","G","G","Y","0","Y","Y","G","Y","B","R","B","R","Y","B","R","B","Y","R","Y","B","R","B","Y","R","Y","B","R","B","Y","G"],"cursorData":"000000000000000000000000000000000000000000000000000000000000000000000000000000","arrowData":"000000000000000000000000000000000000000000000000000000000000000000000000000000","slideText":"Target: 11 Chain","autoDrop":true,"advanceNext":true,"puyoPair":"YY"},{"fieldData":["0","0","0","0","0","0","0","0","0","0","0","0","0","0","0","0","0","0","0","0","0","0","0","0","0","0","0","0","0","0","0","0","0","0","0","0","0","0","0","0","0","0","0","0","0","0","0","0","0","0","0","0","0","0","0","0","0","0","0","0","0","0","0","0","0","0","Y","0","0","0","0","0","Y","0","0","0","0","0"],"fieldOriginal":["0","0","0","0","0","0","0","0","0","0","0","0","0","0","0","0","0","0","0","0","0","0","0","0","0","0","0","0","0","0","0","0","0","0","0","0","0","0","0","0","0","0","0","0","0","0","0","0","0","0","0","0","0","0","0","0","0","0","0","0","0","0","0","0","0","0","Y","0","0","0","0","0","Y","0","0","0","0","0"],"shadowData":["0","0","0","0","0","0","0","0","0","0","0","0","0","0","0","0","0","0","0","0","0","0","B","0","0","0","0","0","Y","B","0","0","0","0","Y","Y","0","0","0","0","Y","B","0","Y","G","0","B","B","G","G","Y","0","Y","Y","G","Y","B","R","B","R","Y","B","R","B","Y","R","Y","B","R","B","Y","R","Y","B","R","B","Y","G"],"cursorData":"000000000000000000000000000000000000000000000000000000000000000000000000000000","arrowData":"000000000000000000000000000000000000000000000000000000000000000000000000000000","slideText":"Target: 11 Chain","autoDrop":true,"advanceNext":true,"puyoPair":"BB"},{"fieldData":["0","0","0","0","0","0","0","0","0","0","0","0","0","0","0","0","0","0","0","0","0","0","0","0","0","0","0","0","0","0","0","0","0","0","0","0","0","0","0","0","0","0","0","0","0","0","0","0","0","0","0","0","0","0","0","0","0","0","0","0","0","0","0","0","0","0","Y","B","0","0","0","0","Y","B","0","0","0","0"],"fieldOriginal":["0","0","0","0","0","0","0","0","0","0","0","0","0","0","0","0","0","0","0","0","0","0","0","0","0","0","0","0","0","0","0","0","0","0","0","0","0","0","0","0","0","0","0","0","0","0","0","0","0","0","0","0","0","0","0","0","0","0","0","0","0","0","0","0","0","0","Y","B","0","0","0","0","Y","B","0","0","0","0"],"shadowData":["0","0","0","0","0","0","0","0","0","0","0","0","0","0","0","0","0","0","0","0","0","0","B","0","0","0","0","0","Y","B","0","0","0","0","Y","Y","0","0","0","0","Y","B","0","Y","G","0","B","B","G","G","Y","0","Y","Y","G","Y","B","R","B","R","Y","B","R","B","Y","R","Y","B","R","B","Y","R","Y","B","R","B","Y","G"],"cursorData":"000000000000000000000000000000000000000000000000000000000000000000000000000000","arrowData":"000000000000000000000000000000000000000000000000000000000000000000000000000000","slideText":"Target: 11 Chain","autoDrop":true,"advanceNext":true,"puyoPair":"RB"},{"fieldData":["0","0","0","0","0","0","0","0","0","0","0","0","0","0","0","0","0","0","0","0","0","0","0","0","0","0","0","0","0","0","0","0","0","0","0","0","0","0","0","0","0","0","0","0","0","0","0","0","0","0","0","0","0","0","0","0","0","0","0","0","0","0","0","0","0","0","Y","B","0","0","0","0","Y","B","R","B","0","0"],"fieldOriginal":["0","0","0","0","0","0","0","0","0","0","0","0","0","0","0","0","0","0","0","0","0","0","0","0","0","0","0","0","0","0","0","0","0","0","0","0","0","0","0","0","0","0","0","0","0","0","0","0","0","0","0","0","0","0","0","0","0","0","0","0","0","0","0","0","0","0","Y","B","0","0","0","0","Y","B","R","B","0","0"],"shadowData":["0","0","0","0","0","0","0","0","0","0","0","0","0","0","0","0","0","0","0","0","0","0","B","0","0","0","0","0","Y","B","0","0","0","0","Y","Y","0","0","0","0","Y","B","0","Y","G","0","B","B","G","G","Y","0","Y","Y","G","Y","B","R","B","R","Y","B","R","B","Y","R","Y","B","R","B","Y","R","Y","B","R","B","Y","G"],"cursorData":"000000000000000000000000000000000000000000000000000000000000000000000000000000","arrowData":"000000000000000000000000000000000000000000000000000000000000000000000000000000","slideText":"Target: 11 Chain","autoDrop":true,"advanceNext":true,"puyoPair":"BY"},{"fieldData":["0","0","0","0","0","0","0","0","0","0","0","0","0","0","0","0","0","0","0","0","0","0","0","0","0","0","0","0","0","0","0","0","0","0","0","0","0","0","0","0","0","0","0","0","0","0","0","0","0","0","0","0","0","0","0","0","0","0","0","0","Y","B","0","0","0","0","Y","B","0","0","0","0","Y","B","R","B","0","0"],"fieldOriginal":["0","0","0","0","0","0","0","0","0","0","0","0","0","0","0","0","0","0","0","0","0","0","0","0","0","0","0","0","0","0","0","0","0","0","0","0","0","0","0","0","0","0","0","0","0","0","0","0","0","0","0","0","0","0","0","0","0","0","0","0","Y","B","0","0","0","0","Y","B","0","0","0","0","Y","B","R","B","0","0"],"shadowData":["0","0","0","0","0","0","0","0","0","0","0","0","0","0","0","0","0","0","0","0","0","0","B","0","0","0","0","0","Y","B","0","0","0","0","Y","Y","0","0","0","0","Y","B","0","Y","G","0","B","B","G","G","Y","0","Y","Y","G","Y","B","R","B","R","Y","B","R","B","Y","R","Y","B","R","B","Y","R","Y","B","R","B","Y","G"],"cursorData":"000000000000000000000000000000000000000000000000000000000000000000000000000000","arrowData":"000000000000000000000000000000000000000000000000000000000000000000000000000000","slideText":"Target: 11 Chain","autoDrop":true,"advanceNext":true,"puyoPair":"YB"},{"fieldData":["0","0","0","0","0","0","0","0","0","0","0","0","0","0","0","0","0","0","0","0","0","0","0","0","0","0","0","0","0","0","0","0","0","0","0","0","0","0","0","0","0","0","0","0","0","0","0","0","0","0","0","0","0","0","0","0","0","0","0","0","Y","B","0","0","0","0","Y","B","0","B","0","0","Y","B","R","B","Y","0"],"fieldOriginal":["0","0","0","0","0","0","0","0","0","0","0","0","0","0","0","0","0","0","0","0","0","0","0","0","0","0","0","0","0","0","0","0","0","0","0","0","0","0","0","0","0","0","0","0","0","0","0","0","0","0","0","0","0","0","0","0","0","0","0","0","Y","B","0","0","0","0","Y","B","0","B","0","0","Y","B","R","B","Y","0"],"shadowData":["0","0","0","0","0","0","0","0","0","0","0","0","0","0","0","0","0","0","0","0","0","0","B","0","0","0","0","0","Y","B","0","0","0","0","Y","Y","0","0","0","0","Y","B","0","Y","G","0","B","B","G","G","Y","0","Y","Y","G","Y","B","R","B","R","Y","B","R","B","Y","R","Y","B","R","B","Y","R","Y","B","R","B","Y","G"],"cursorData":"000000000000000000000000000000000000000000000000000000000000000000000000000000","arrowData":"000000000000000000000000000000000000000000000000000000000000000000000000000000","slideText":"Target: 11 Chain","autoDrop":true,"advanceNext":true,"puyoPair":"YR"},{"fieldData":["0","0","0","0","0","0","0","0","0","0","0","0","0","0","0","0","0","0","0","0","0","0","0","0","0","0","0","0","0","0","0","0","0","0","0","0","0","0","0","0","0","0","0","0","0","0","0","0","0","0","0","0","0","0","0","Y","0","0","0","0","Y","B","0","0","0","0","Y","B","R","B","0","0","Y","B","R","B","Y","0"],"fieldOriginal":["0","0","0","0","0","0","0","0","0","0","0","0","0","0","0","0","0","0","0","0","0","0","0","0","0","0","0","0","0","0","0","0","0","0","0","0","0","0","0","0","0","0","0","0","0","0","0","0","0","0","0","0","0","0","0","Y","0","0","0","0","Y","B","0","0","0","0","Y","B","R","B","0","0","Y","B","R","B","Y","0"],"shadowData":["0","0","0","0","0","0","0","0","0","0","0","0","0","0","0","0","0","0","0","0","0","0","B","0","0","0","0","0","Y","B","0","0","0","0","Y","Y","0","0","0","0","Y","B","0","Y","G","0","B","B","G","G","Y","0","Y","Y","G","Y","B","R","B","R","Y","B","R","B","Y","R","Y","B","R","B","Y","R","Y","B","R","B","Y","G"],"cursorData":"000000000000000000000000000000000000000000000000000000000000000000000000000000","arrowData":"000000000000000000000000000000000000000000000000000000000000000000000000000000","slideText":"Target: 11 Chain","autoDrop":true,"advanceNext":true,"puyoPair":"GR"},{"fieldData":["0","0","0","0","0","0","0","0","0","0","0","0","0","0","0","0","0","0","0","0","0","0","0","0","0","0","0","0","0","0","0","0","0","0","0","0","0","0","0","0","0","0","0","0","0","0","0","0","0","0","0","0","0","0","0","Y","0","0","0","0","Y","B","0","0","0","0","Y","B","R","B","0","R","Y","B","R","B","Y","G"],"fieldOriginal":["0","0","0","0","0","0","0","0","0","0","0","0","0","0","0","0","0","0","0","0","0","0","0","0","0","0","0","0","0","0","0","0","0","0","0","0","0","0","0","0","0","0","0","0","0","0","0","0","0","0","0","0","0","0","0","Y","0","0","0","0","Y","B","0","0","0","0","Y","B","R","B","0","R","Y","B","R","B","Y","G"],"shadowData":["0","0","0","0","0","0","0","0","0","0","0","0","0","0","0","0","0","0","0","0","0","0","B","0","0","0","0","0","Y","B","0","0","0","0","Y","Y","0","0","0","0","Y","B","0","Y","G","0","B","B","G","G","Y","0","Y","Y","G","Y","B","R","B","R","Y","B","R","B","Y","R","Y","B","R","B","Y","R","Y","B","R","B","Y","G"],"cursorData":"000000000000000000000000000000000000000000000000000000000000000000000000000000","arrowData":"000000000000000000000000000000000000000000000000000000000000000000000000000000","slideText":"Target: 11 Chain","autoDrop":true,"advanceNext":true,"puyoPair":"YR"},{"fieldData":["0","0","0","0","0","0","0","0","0","0","0","0","0","0","0","0","0","0","0","0","0","0","0","0","0","0","0","0","0","0","0","0","0","0","0","0","0","0","0","0","0","0","0","0","0","0","0","0","0","0","0","0","0","0","0","Y","0","0","0","0","Y","B","0","0","0","R","Y","B","R","B","Y","R","Y","B","R","B","Y","G"],"fieldOriginal":["0","0","0","0","0","0","0","0","0","0","0","0","0","0","0","0","0","0","0","0","0","0","0","0","0","0","0","0","0","0","0","0","0","0","0","0","0","0","0","0","0","0","0","0","0","0","0","0","0","0","0","0","0","0","0","Y","0","0","0","0","Y","B","0","0","0","R","Y","B","R","B","Y","R","Y","B","R","B","Y","G"],"shadowData":["0","0","0","0","0","0","0","0","0","0","0","0","0","0","0","0","0","0","0","0","0","0","B","0","0","0","0","0","Y","B","0","0","0","0","Y","Y","0","0","0","0","Y","B","0","Y","G","0","B","B","G","G","Y","0","Y","Y","G","Y","B","R","B","R","Y","B","R","B","Y","R","Y","B","R","B","Y","R","Y","B","R","B","Y","G"],"cursorData":"000000000000000000000000000000000000000000000000000000000000000000000000000000","arrowData":"000000000000000000000000000000000000000000000000000000000000000000000000000000","slideText":"Target: 11 Chain","autoDrop":true,"advanceNext":true,"puyoPair":"YR"},{"fieldData":["0","0","0","0","0","0","0","0","0","0","0","0","0","0","0","0","0","0","0","0","0","0","0","0","0","0","0","0","0","0","0","0","0","0","0","0","0","0","0","0","0","0","0","0","0","0","0","0","0","0","0","0","0","0","0","Y","0","0","0","R","Y","B","0","0","Y","R","Y","B","R","B","Y","R","Y","B","R","B","Y","G"],"fieldOriginal":["0","0","0","0","0","0","0","0","0","0","0","0","0","0","0","0","0","0","0","0","0","0","0","0","0","0","0","0","0","0","0","0","0","0","0","0","0","0","0","0","0","0","0","0","0","0","0","0","0","0","0","0","0","0","0","Y","0","0","0","R","Y","B","0","0","Y","R","Y","B","R","B","Y","R","Y","B","R","B","Y","G"],"shadowData":["0","0","0","0","0","0","0","0","0","0","0","0","0","0","0","0","0","0","0","0","0","0","B","0","0","0","0","0","Y","B","0","0","0","0","Y","Y","0","0","0","0","Y","B","0","Y","G","0","B","B","G","G","Y","0","Y","Y","G","Y","B","R","B","R","Y","B","R","B","Y","R","Y","B","R","B","Y","R","Y","B","R","B","Y","G"],"cursorData":"000000000000000000000000000000000000000000000000000000000000000000000000000000","arrowData":"000000000000000000000000000000000000000000000000000000000000000000000000000000","slideText":"Target: 11 Chain","autoDrop":true,"advanceNext":true,"puyoPair":"BR"},{"fieldData":["0","0","0","0","0","0","0","0","0","0","0","0","0","0","0","0","0","0","0","0","0","0","0","0","0","0","0","0","0","0","0","0","0","0","0","0","0","0","0","0","0","0","0","0","0","0","0","0","0","0","0","0","0","0","0","Y","B","0","0","R","Y","B","R","0","Y","R","Y","B","R","B","Y","R","Y","B","R","B","Y","G"],"fieldOriginal":["0","0","0","0","0","0","0","0","0","0","0","0","0","0","0","0","0","0","0","0","0","0","0","0","0","0","0","0","0","0","0","0","0","0","0","0","0","0","0","0","0","0","0","0","0","0","0","0","0","0","0","0","0","0","0","Y","B","0","0","R","Y","B","R","0","Y","R","Y","B","R","B","Y","R","Y","B","R","B","Y","G"],"shadowData":["0","0","0","0","0","0","0","0","0","0","0","0","0","0","0","0","0","0","0","0","0","0","B","0","0","0","0","0","Y","B","0","0","0","0","Y","Y","0","0","0","0","Y","B","0","Y","G","0","B","B","G","G","Y","0","Y","Y","G","Y","B","R","B","R","Y","B","R","B","Y","R","Y","B","R","B","Y","R","Y","B","R","B","Y","G"],"cursorData":"000000000000000000000000000000000000000000000000000000000000000000000000000000","arrowData":"000000000000000000000000000000000000000000000000000000000000000000000000000000","slideText":"Target: 11 Chain","autoDrop":true,"advanceNext":true,"puyoPair":"YB"},{"fieldData":["0","0","0","0","0","0","0","0","0","0","0","0","0","0","0","0","0","0","0","0","0","0","0","0","0","0","0","0","0","0","0","0","0","0","0","0","0","0","0","0","0","0","0","0","0","0","0","0","0","0","Y","0","0","0","0","Y","B","0","0","R","Y","B","R","B","Y","R","Y","B","R","B","Y","R","Y","B","R","B","Y","G"],"fieldOriginal":["0","0","0","0","0","0","0","0","0","0","0","0","0","0","0","0","0","0","0","0","0","0","0","0","0","0","0","0","0","0","0","0","0","0","0","0","0","0","0","0","0","0","0","0","0","0","0","0","0","0","Y","0","0","0","0","Y","B","0","0","R","Y","B","R","B","Y","R","Y","B","R","B","Y","R","Y","B","R","B","Y","G"],"shadowData":["0","0","0","0","0","0","0","0","0","0","0","0","0","0","0","0","0","0","0","0","0","0","B","0","0","0","0","0","Y","B","0","0","0","0","Y","Y","0","0","0","0","Y","B","0","Y","G","0","B","B","G","G","Y","0","Y","Y","G","Y","B","R","B","R","Y","B","R","B","Y","R","Y","B","R","B","Y","R","Y","B","R","B","Y","G"],"cursorData":"000000000000000000000000000000000000000000000000000000000000000000000000000000","arrowData":"000000000000000000000000000000000000000000000000000000000000000000000000000000","slideText":"Target: 11 Chain","autoDrop":true,"advanceNext":true,"puyoPair":"YB"},{"fieldData":["0","0","0","0","0","0","0","0","0","0","0","0","0","0","0","0","0","0","0","0","0","0","0","0","0","0","0","0","0","0","0","0","0","0","0","0","0","0","0","0","0","0","0","0","0","0","0","0","0","0","Y","0","0","Y","0","Y","B","0","B","R","Y","B","R","B","Y","R","Y","B","R","B","Y","R","Y","B","R","B","Y","G"],"fieldOriginal":["0","0","0","0","0","0","0","0","0","0","0","0","0","0","0","0","0","0","0","0","0","0","0","0","0","0","0","0","0","0","0","0","0","0","0","0","0","0","0","0","0","0","0","0","0","0","0","0","0","0","Y","0","0","Y","0","Y","B","0","B","R","Y","B","R","B","Y","R","Y","B","R","B","Y","R","Y","B","R","B","Y","G"],"shadowData":["0","0","0","0","0","0","0","0","0","0","0","0","0","0","0","0","0","0","0","0","0","0","B","0","0","0","0","0","Y","B","0","0","0","0","Y","Y","0","0","0","0","Y","B","0","Y","G","0","B","B","G","G","Y","0","Y","Y","G","Y","B","R","B","R","Y","B","R","B","Y","R","Y","B","R","B","Y","R","Y","B","R","B","Y","G"],"cursorData":"000000000000000000000000000000000000000000000000000000000000000000000000000000","arrowData":"000000000000000000000000000000000000000000000000000000000000000000000000000000","slideText":"Target: 11 Chain","autoDrop":true,"advanceNext":true,"puyoPair":"BB"},{"fieldData":["0","0","0","0","0","0","0","0","0","0","0","0","0","0","0","0","0","0","0","0","0","0","0","0","0","0","0","0","0","0","0","0","0","0","0","0","0","0","0","0","0","B","0","0","0","0","0","B","0","0","Y","0","0","Y","0","Y","B","0","B","R","Y","B","R","B","Y","R","Y","B","R","B","Y","R","Y","B","R","B","Y","G"],"fieldOriginal":["0","0","0","0","0","0","0","0","0","0","0","0","0","0","0","0","0","0","0","0","0","0","0","0","0","0","0","0","0","0","0","0","0","0","0","0","0","0","0","0","0","B","0","0","0","0","0","B","0","0","Y","0","0","Y","0","Y","B","0","B","R","Y","B","R","B","Y","R","Y","B","R","B","Y","R","Y","B","R","B","Y","G"],"shadowData":["0","0","0","0","0","0","0","0","0","0","0","0","0","0","0","0","0","0","0","0","0","0","B","0","0","0","0","0","Y","B","0","0","0","0","Y","Y","0","0","0","0","Y","B","0","Y","G","0","B","B","G","G","Y","0","Y","Y","G","Y","B","R","B","R","Y","B","R","B","Y","R","Y","B","R","B","Y","R","Y","B","R","B","Y","G"],"cursorData":"000000000000000000000000000000000000000000000000000000000000000000000000000000","arrowData":"000000000000000000000000000000000000000000000000000000000000000000000000000000","slideText":"Target: 11 Chain","autoDrop":true,"advanceNext":true,"puyoPair":"BY"},{"fieldData":["0","0","0","0","0","0","0","0","0","0","0","0","0","0","0","0","0","0","0","0","0","0","0","0","0","0","0","0","0","0","0","0","0","0","0","0","0","0","0","0","0","B","0","0","0","0","B","B","0","0","Y","0","Y","Y","0","Y","B","0","B","R","Y","B","R","B","Y","R","Y","B","R","B","Y","R","Y","B","R","B","Y","G"],"fieldOriginal":["0","0","0","0","0","0","0","0","0","0","0","0","0","0","0","0","0","0","0","0","0","0","0","0","0","0","0","0","0","0","0","0","0","0","0","0","0","0","0","0","0","B","0","0","0","0","B","B","0","0","Y","0","Y","Y","0","Y","B","0","B","R","Y","B","R","B","Y","R","Y","B","R","B","Y","R","Y","B","R","B","Y","G"],"shadowData":["0","0","0","0","0","0","0","0","0","0","0","0","0","0","0","0","0","0","0","0","0","0","B","0","0","0","0","0","Y","B","0","0","0","0","Y","Y","0","0","0","0","Y","B","0","Y","G","0","B","B","G","G","Y","0","Y","Y","G","Y","B","R","B","R","Y","B","R","B","Y","R","Y","B","R","B","Y","R","Y","B","R","B","Y","G"],"cursorData":"000000000000000000000000000000000000000000000000000000000000000000000000000000","arrowData":"000000000000000000000000000000000000000000000000000000000000000000000000000000","slideText":"Target: 11 Chain","autoDrop":true,"advanceNext":true,"puyoPair":"GG"},{"fieldData":["0","0","0","0","0","0","0","0","0","0","0","0","0","0","0","0","0","0","0","0","0","0","0","0","0","0","0","0","0","0","0","0","0","0","0","0","0","0","0","0","0","B","0","0","0","0","B","B","G","0","Y","0","Y","Y","G","Y","B","0","B","R","Y","B","R","B","Y","R","Y","B","R","B","Y","R","Y","B","R","B","Y","G"],"fieldOriginal":["0","0","0","0","0","0","0","0","0","0","0","0","0","0","0","0","0","0","0","0","0","0","0","0","0","0","0","0","0","0","0","0","0","0","0","0","0","0","0","0","0","B","0","0","0","0","B","B","G","0","Y","0","Y","Y","G","Y","B","0","B","R","Y","B","R","B","Y","R","Y","B","R","B","Y","R","Y","B","R","B","Y","G"],"shadowData":["0","0","0","0","0","0","0","0","0","0","0","0","0","0","0","0","0","0","0","0","0","0","B","0","0","0","0","0","Y","B","0","0","0","0","Y","Y","0","0","0","0","Y","B","0","Y","G","0","B","B","G","G","Y","0","Y","Y","G","Y","B","R","B","R","Y","B","R","B","Y","R","Y","B","R","B","Y","R","Y","B","R","B","Y","G"],"cursorData":"000000000000000000000000000000000000000000000000000000000000000000000000000000","arrowData":"000000000000000000000000000000000000000000000000000000000000000000000000000000","slideText":"Target: 11 Chain","autoDrop":true,"advanceNext":true,"puyoPair":"RG"},{"fieldData":["0","0","0","0","0","0","0","0","0","0","0","0","0","0","0","0","0","0","0","0","0","0","0","0","0","0","0","0","0","0","0","0","0","0","0","0","0","0","0","0","0","B","0","0","G","0","B","B","G","0","Y","0","Y","Y","G","Y","B","R","B","R","Y","B","R","B","Y","R","Y","B","R","B","Y","R","Y","B","R","B","Y","G"],"fieldOriginal":["0","0","0","0","0","0","0","0","0","0","0","0","0","0","0","0","0","0","0","0","0","0","0","0","0","0","0","0","0","0","0","0","0","0","0","0","0","0","0","0","0","B","0","0","G","0","B","B","G","0","Y","0","Y","Y","G","Y","B","R","B","R","Y","B","R","B","Y","R","Y","B","R","B","Y","R","Y","B","R","B","Y","G"],"shadowData":["0","0","0","0","0","0","0","0","0","0","0","0","0","0","0","0","0","0","0","0","0","0","B","0","0","0","0","0","Y","B","0","0","0","0","Y","Y","0","0","0","0","Y","B","0","Y","G","0","B","B","G","G","Y","0","Y","Y","G","Y","B","R","B","R","Y","B","R","B","Y","R","Y","B","R","B","Y","R","Y","B","R","B","Y","G"],"cursorData":"000000000000000000000000000000000000000000000000000000000000000000000000000000","arrowData":"000000000000000000000000000000000000000000000000000000000000000000000000000000","slideText":"Target: 11 Chain","autoDrop":true,"advanceNext":true,"puyoPair":"GY"},{"fieldData":["0","0","0","0","0","0","0","0","0","0","0","0","0","0","0","0","0","0","0","0","0","0","0","0","0","0","0","0","0","0","0","0","0","0","0","0","0","0","0","0","0","B","0","Y","G","0","B","B","G","G","Y","0","Y","Y","G","Y","B","R","B","R","Y","B","R","B","Y","R","Y","B","R","B","Y","R","Y","B","R","B","Y","G"],"fieldOriginal":["0","0","0","0","0","0","0","0","0","0","0","0","0","0","0","0","0","0","0","0","0","0","0","0","0","0","0","0","0","0","0","0","0","0","0","0","0","0","0","0","0","B","0","Y","G","0","B","B","G","G","Y","0","Y","Y","G","Y","B","R","B","R","Y","B","R","B","Y","R","Y","B","R","B","Y","R","Y","B","R","B","Y","G"],"shadowData":["0","0","0","0","0","0","0","0","0","0","0","0","0","0","0","0","0","0","0","0","0","0","B","0","0","0","0","0","Y","B","0","0","0","0","Y","Y","0","0","0","0","Y","B","0","Y","G","0","B","B","G","G","Y","0","Y","Y","G","Y","B","R","B","R","Y","B","R","B","Y","R","Y","B","R","B","Y","R","Y","B","R","B","Y","G"],"cursorData":"000000000000000000000000000000000000000000000000000000000000000000000000000000","arrowData":"000000000000000000000000000000000000000000000000000000000000000000000000000000","slideText":"Target: 11 Chain","autoDrop":true,"advanceNext":true,"puyoPair":"BY"},{"fieldData":["0","0","0","0","0","0","0","0","0","0","0","0","0","0","0","0","0","0","0","0","0","0","0","0","0","0","0","0","0","B","0","0","0","0","0","Y","0","0","0","0","0","B","0","Y","G","0","B","B","G","G","Y","0","Y","Y","G","Y","B","R","B","R","Y","B","R","B","Y","R","Y","B","R","B","Y","R","Y","B","R","B","Y","G"],"fieldOriginal":["0","0","0","0","0","0","0","0","0","0","0","0","0","0","0","0","0","0","0","0","0","0","0","0","0","0","0","0","0","B","0","0","0","0","0","Y","0","0","0","0","0","B","0","Y","G","0","B","B","G","G","Y","0","Y","Y","G","Y","B","R","B","R","Y","B","R","B","Y","R","Y","B","R","B","Y","R","Y","B","R","B","Y","G"],"shadowData":["0","0","0","0","0","0","0","0","0","0","0","0","0","0","0","0","0","0","0","0","0","0","B","0","0","0","0","0","Y","B","0","0","0","0","Y","Y","0","0","0","0","Y","B","0","Y","G","0","B","B","G","G","Y","0","Y","Y","G","Y","B","R","B","R","Y","B","R","B","Y","R","Y","B","R","B","Y","R","Y","B","R","B","Y","G"],"cursorData":"000000000000000000000000000000000000000000000000000000000000000000000000000000","arrowData":"000000000000000000000000000000000000000000000000000000000000000000000000000000","slideText":"Target: 11 Chain","autoDrop":true,"advanceNext":true,"puyoPair":"YY"},{"fieldData":["0","0","0","0","0","0","0","0","0","0","0","0","0","0","0","0","0","0","0","0","0","0","0","0","0","0","0","0","0","B","0","0","0","0","Y","Y","0","0","0","0","Y","B","0","Y","G","0","B","B","G","G","Y","0","Y","Y","G","Y","B","R","B","R","Y","B","R","B","Y","R","Y","B","R","B","Y","R","Y","B","R","B","Y","G"],"fieldOriginal":["0","0","0","0","0","0","0","0","0","0","0","0","0","0","0","0","0","0","0","0","0","0","0","0","0","0","0","0","0","B","0","0","0","0","Y","Y","0","0","0","0","Y","B","0","Y","G","0","B","B","G","G","Y","0","Y","Y","G","Y","B","R","B","R","Y","B","R","B","Y","R","Y","B","R","B","Y","R","Y","B","R","B","Y","G"],"shadowData":["0","0","0","0","0","0","0","0","0","0","0","0","0","0","0","0","0","0","0","0","0","0","B","0","0","0","0","0","Y","B","0","0","0","0","Y","Y","0","0","0","0","Y","B","0","Y","G","0","B","B","G","G","Y","0","Y","Y","G","Y","B","R","B","R","Y","B","R","B","Y","R","Y","B","R","B","Y","R","Y","B","R","B","Y","G"],"cursorData":"000000000000000000000000000000000000000000000000000000000000000000000000000000","arrowData":"000000000000000000000000000000000000000000000000000000000000000000000000000000","slideText":"Target: 11 Chain","autoDrop":true,"advanceNext":true,"puyoPair":"YB"},{"fieldData":["0","0","0","0","0","0","0","0","0","0","0","0","0","0","0","0","0","0","0","0","0","0","B","0","0","0","0","0","Y","B","0","0","0","0","Y","Y","0","0","0","0","Y","B","0","Y","G","0","B","B","G","G","Y","0","Y","Y","G","Y","B","R","B","R","Y","B","R","B","Y","R","Y","B","R","B","Y","R","Y","B","R","B","Y","G"],"fieldOriginal":["0","0","0","0","0","0","0","0","0","0","0","0","0","0","0","0","0","0","0","0","0","0","B","0","0","0","0","0","Y","B","0","0","0","0","Y","Y","0","0","0","0","Y","B","0","Y","G","0","B","B","G","G","Y","0","Y","Y","G","Y","B","R","B","R","Y","B","R","B","Y","R","Y","B","R","B","Y","R","Y","B","R","B","Y","G"],"shadowData":["0","0","0","0","0","0","0","0","0","0","0","0","0","0","0","0","0","0","0","R","G","B","0","G","0","R","R","R","0","G","0","R","G","G","Y","Y","R","R","B","G","Y","R","Y","Y","G","B","B","R","G","G","Y","G","Y","Y","G","Y","B","R","B","R","Y","B","R","B","Y","R","Y","B","R","B","Y","R","Y","B","R","B","Y","G"],"cursorData":"000000000000000000000000000000000000000000000000000000000000000000000000000000","arrowData":"000000000000000000000000000000000000000000000000000000000000000000000000000000","slideText":"Target: 11 Chain","autoDrop":true,"advanceNext":true,"puyoPair":"GB"},{"fieldData":["0","0","0","0","0","0","0","0","0","0","0","0","0","0","0","0","0","0","0","0","0","0","0","0","0","0","0","0","0","0","0","0","0","0","0","0","0","0","0","0","0","0","0","Y","G","B","0","0","G","G","Y","G","Y","Y","G","Y","B","R","B","R","Y","B","R","B","Y","R","Y","B","R","B","Y","R","Y","B","R","B","Y","G"],"fieldOriginal":["0","0","0","0","0","0","0","0","0","0","0","0","0","0","0","0","0","0","0","0","0","0","0","0","0","0","0","0","0","0","0","0","0","0","0","0","0","0","0","0","0","0","0","Y","G","B","0","0","G","G","Y","G","Y","Y","G","Y","B","R","B","R","Y","B","R","B","Y","R","Y","B","R","B","Y","R","Y","B","R","B","Y","G"],"shadowData":["0","0","0","0","0","0","0","0","0","0","0","0","0","0","0","0","0","0","0","R","G","B","0","G","0","R","R","R","0","G","0","R","G","G","Y","Y","R","R","B","G","Y","R","Y","Y","G","B","B","R","G","G","Y","G","Y","Y","G","Y","B","R","B","R","Y","B","R","B","Y","R","Y","B","R","B","Y","R","Y","B","R","B","Y","G"],"cursorData":"000000000000000000000000000000000000000000000000000000000000000000000000000000","arrowData":"000000000000000000000000000000000000000000000000000000000000000000000000000000","slideText":"Target: 11 Chain","autoDrop":true,"advanceNext":true,"puyoPair":"RB"},{"fieldData":["0","0","0","0","0","0","0","0","0","0","0","0","0","0","0","0","0","0","0","0","0","0","0","0","0","0","0","0","0","0","0","0","0","0","0","0","0","0","0","0","0","0","0","Y","G","B","B","R","G","G","Y","G","Y","Y","G","Y","B","R","B","R","Y","B","R","B","Y","R","Y","B","R","B","Y","R","Y","B","R","B","Y","G"],"fieldOriginal":["0","0","0","0","0","0","0","0","0","0","0","0","0","0","0","0","0","0","0","0","0","0","0","0","0","0","0","0","0","0","0","0","0","0","0","0","0","0","0","0","0","0","0","Y","G","B","B","R","G","G","Y","G","Y","Y","G","Y","B","R","B","R","Y","B","R","B","Y","R","Y","B","R","B","Y","R","Y","B","R","B","Y","G"],"shadowData":["0","0","0","0","0","0","0","0","0","0","0","0","0","0","0","0","0","0","0","R","G","B","0","G","0","R","R","R","0","G","0","R","G","G","Y","Y","R","R","B","G","Y","R","Y","Y","G","B","B","R","G","G","Y","G","Y","Y","G","Y","B","R","B","R","Y","B","R","B","Y","R","Y","B","R","B","Y","R","Y","B","R","B","Y","G"],"cursorData":"000000000000000000000000000000000000000000000000000000000000000000000000000000","arrowData":"000000000000000000000000000000000000000000000000000000000000000000000000000000","slideText":"Target: 11 Chain","autoDrop":true,"advanceNext":true,"puyoPair":"YY"},{"fieldData":["0","0","0","0","0","0","0","0","0","0","0","0","0","0","0","0","0","0","0","0","0","0","0","0","0","0","0","0","0","0","0","0","0","0","Y","0","0","0","0","0","Y","0","0","Y","G","B","B","R","G","G","Y","G","Y","Y","G","Y","B","R","B","R","Y","B","R","B","Y","R","Y","B","R","B","Y","R","Y","B","R","B","Y","G"],"fieldOriginal":["0","0","0","0","0","0","0","0","0","0","0","0","0","0","0","0","0","0","0","0","0","0","0","0","0","0","0","0","0","0","0","0","0","0","Y","0","0","0","0","0","Y","0","0","Y","G","B","B","R","G","G","Y","G","Y","Y","G","Y","B","R","B","R","Y","B","R","B","Y","R","Y","B","R","B","Y","R","Y","B","R","B","Y","G"],"shadowData":["0","0","0","0","0","0","0","0","0","0","0","0","0","0","0","0","0","0","0","R","G","B","0","G","0","R","R","R","0","G","0","R","G","G","Y","Y","R","R","B","G","Y","R","Y","Y","G","B","B","R","G","G","Y","G","Y","Y","G","Y","B","R","B","R","Y","B","R","B","Y","R","Y","B","R","B","Y","R","Y","B","R","B","Y","G"],"cursorData":"000000000000000000000000000000000000000000000000000000000000000000000000000000","arrowData":"000000000000000000000000000000000000000000000000000000000000000000000000000000","slideText":"The reds in the 6th column have to be two rows high to create a separation for the yellows.","autoDrop":true,"advanceNext":true,"puyoPair":"YR"},{"fieldData":["0","0","0","0","0","0","0","0","0","0","0","0","0","0","0","0","0","0","0","0","0","0","0","0","0","0","0","0","0","0","0","0","0","0","Y","Y","0","0","0","0","Y","R","0","Y","G","B","B","R","G","G","Y","G","Y","Y","G","Y","B","R","B","R","Y","B","R","B","Y","R","Y","B","R","B","Y","R","Y","B","R","B","Y","G"],"fieldOriginal":["0","0","0","0","0","0","0","0","0","0","0","0","0","0","0","0","0","0","0","0","0","0","0","0","0","0","0","0","0","0","0","0","0","0","Y","Y","0","0","0","0","Y","R","0","Y","G","B","B","R","G","G","Y","G","Y","Y","G","Y","B","R","B","R","Y","B","R","B","Y","R","Y","B","R","B","Y","R","Y","B","R","B","Y","G"],"shadowData":["0","0","0","0","0","0","0","0","0","0","0","0","0","0","0","0","0","0","0","R","G","B","0","G","0","R","R","R","0","G","0","R","G","G","Y","Y","R","R","B","G","Y","R","Y","Y","G","B","B","R","G","G","Y","G","Y","Y","G","Y","B","R","B","R","Y","B","R","B","Y","R","Y","B","R","B","Y","R","Y","B","R","B","Y","G"],"cursorData":"000000000000000000000000000000000000000000000000000000000000000000000000000000","arrowData":"000000000000000000000000000000000000000000000000000000000000000000000000000000","slideText":"The reds in the 6th column have to be two rows high to create a separation for the yellows.","autoDrop":true,"advanceNext":true,"puyoPair":"RR"},{"fieldData":["0","0","0","0","0","0","0","0","0","0","0","0","0","0","0","0","0","0","0","0","0","0","0","0","0","0","0","0","0","0","0","R","0","0","Y","Y","0","R","0","0","Y","R","0","Y","G","B","B","R","G","G","Y","G","Y","Y","G","Y","B","R","B","R","Y","B","R","B","Y","R","Y","B","R","B","Y","R","Y","B","R","B","Y","G"],"fieldOriginal":["0","0","0","0","0","0","0","0","0","0","0","0","0","0","0","0","0","0","0","0","0","0","0","0","0","0","0","0","0","0","0","R","0","0","Y","Y","0","R","0","0","Y","R","0","Y","G","B","B","R","G","G","Y","G","Y","Y","G","Y","B","R","B","R","Y","B","R","B","Y","R","Y","B","R","B","Y","R","Y","B","R","B","Y","G"],"shadowData":["0","0","0","0","0","0","0","0","0","0","0","0","0","0","0","0","0","0","0","R","G","B","0","G","0","R","R","R","0","G","0","R","G","G","Y","Y","R","R","B","G","Y","R","Y","Y","G","B","B","R","G","G","Y","G","Y","Y","G","Y","B","R","B","R","Y","B","R","B","Y","R","Y","B","R","B","Y","R","Y","B","R","B","Y","G"],"cursorData":"000000000000000000000000000000000000000000000000000000000000000000000000000000","arrowData":"000000000000000000000000000000000000000000000000000000000000000000000000000000","slideText":"The reds in the 6th column have to be two rows high to create a separation for the yellows.","autoDrop":true,"advanceNext":true,"puyoPair":"GG"},{"fieldData":["0","0","0","0","0","0","0","0","0","0","0","0","0","0","0","0","0","0","0","0","0","0","0","0","0","0","0","0","0","0","0","R","0","G","Y","Y","0","R","0","G","Y","R","0","Y","G","B","B","R","G","G","Y","G","Y","Y","G","Y","B","R","B","R","Y","B","R","B","Y","R","Y","B","R","B","Y","R","Y","B","R","B","Y","G"],"fieldOriginal":["0","0","0","0","0","0","0","0","0","0","0","0","0","0","0","0","0","0","0","0","0","0","0","0","0","0","0","0","0","0","0","R","0","G","Y","Y","0","R","0","G","Y","R","0","Y","G","B","B","R","G","G","Y","G","Y","Y","G","Y","B","R","B","R","Y","B","R","B","Y","R","Y","B","R","B","Y","R","Y","B","R","B","Y","G"],"shadowData":["0","0","0","0","0","0","0","0","0","0","0","0","0","0","0","0","0","0","0","R","G","B","0","G","0","R","R","R","0","G","0","R","G","G","Y","Y","R","R","B","G","Y","R","Y","Y","G","B","B","R","G","G","Y","G","Y","Y","G","Y","B","R","B","R","Y","B","R","B","Y","R","Y","B","R","B","Y","R","Y","B","R","B","Y","G"],"cursorData":"000000000000000000000000000000000000000000000000000000000000000000000000000000","arrowData":"000000000000000000000000000000000000000000000000000000000000000000000000000000","slideText":"","autoDrop":true,"advanceNext":true,"puyoPair":"GB"},{"fieldData":["0","0","0","0","0","0","0","0","0","0","0","0","0","0","0","0","0","0","0","0","0","0","0","0","0","0","0","0","0","0","0","R","G","G","Y","Y","0","R","B","G","Y","R","0","Y","G","B","B","R","G","G","Y","G","Y","Y","G","Y","B","R","B","R","Y","B","R","B","Y","R","Y","B","R","B","Y","R","Y","B","R","B","Y","G"],"fieldOriginal":["0","0","0","0","0","0","0","0","0","0","0","0","0","0","0","0","0","0","0","0","0","0","0","0","0","0","0","0","0","0","0","R","G","G","Y","Y","0","R","B","G","Y","R","0","Y","G","B","B","R","G","G","Y","G","Y","Y","G","Y","B","R","B","R","Y","B","R","B","Y","R","Y","B","R","B","Y","R","Y","B","R","B","Y","G"],"shadowData":["0","0","0","0","0","0","0","0","0","0","0","0","0","0","0","0","0","0","0","R","G","B","0","G","0","R","R","R","0","G","0","R","G","G","Y","Y","R","R","B","G","Y","R","Y","Y","G","B","B","R","G","G","Y","G","Y","Y","G","Y","B","R","B","R","Y","B","R","B","Y","R","Y","B","R","B","Y","R","Y","B","R","B","Y","G"],"cursorData":"000000000000000000000000000000000000000000000000000000000000000000000000000000","arrowData":"000000000000000000000000000000000000000000000000000000000000000000000000000000","slideText":"","autoDrop":true,"advanceNext":true,"puyoPair":"RG"},{"fieldData":["0","0","0","0","0","0","0","0","0","0","0","0","0","0","0","0","0","0","0","0","G","0","0","0","0","0","R","0","0","0","0","R","G","G","Y","Y","0","R","B","G","Y","R","0","Y","G","B","B","R","G","G","Y","G","Y","Y","G","Y","B","R","B","R","Y","B","R","B","Y","R","Y","B","R","B","Y","R","Y","B","R","B","Y","G"],"fieldOriginal":["0","0","0","0","0","0","0","0","0","0","0","0","0","0","0","0","0","0","0","0","G","0","0","0","0","0","R","0","0","0","0","R","G","G","Y","Y","0","R","B","G","Y","R","0","Y","G","B","B","R","G","G","Y","G","Y","Y","G","Y","B","R","B","R","Y","B","R","B","Y","R","Y","B","R","B","Y","R","Y","B","R","B","Y","G"],"shadowData":["0","0","0","0","0","0","0","0","0","0","0","0","0","0","0","0","0","0","0","R","G","B","0","G","0","R","R","R","0","G","0","R","G","G","Y","Y","R","R","B","G","Y","R","Y","Y","G","B","B","R","G","G","Y","G","Y","Y","G","Y","B","R","B","R","Y","B","R","B","Y","R","Y","B","R","B","Y","R","Y","B","R","B","Y","G"],"cursorData":"000000000000000000000000000000000000000000000000000000000000000000000000000000","arrowData":"000000000000000000000000000000000000000000000000000000000000000000000000000000","slideText":"","autoDrop":true,"advanceNext":true,"puyoPair":"YR"},{"fieldData":["0","0","0","0","0","0","0","0","0","0","0","0","0","0","0","0","0","0","0","0","G","0","0","0","0","0","R","0","0","0","0","R","G","G","Y","Y","R","R","B","G","Y","R","Y","Y","G","B","B","R","G","G","Y","G","Y","Y","G","Y","B","R","B","R","Y","B","R","B","Y","R","Y","B","R","B","Y","R","Y","B","R","B","Y","G"],"fieldOriginal":["0","0","0","0","0","0","0","0","0","0","0","0","0","0","0","0","0","0","0","0","G","0","0","0","0","0","R","0","0","0","0","R","G","G","Y","Y","R","R","B","G","Y","R","Y","Y","G","B","B","R","G","G","Y","G","Y","Y","G","Y","B","R","B","R","Y","B","R","B","Y","R","Y","B","R","B","Y","R","Y","B","R","B","Y","G"],"shadowData":["0","0","0","0","0","0","0","0","0","0","0","0","0","0","0","0","0","0","0","R","G","B","0","G","0","R","R","R","0","G","0","R","G","G","Y","Y","R","R","B","G","Y","R","Y","Y","G","B","B","R","G","G","Y","G","Y","Y","G","Y","B","R","B","R","Y","B","R","B","Y","R","Y","B","R","B","Y","R","Y","B","R","B","Y","G"],"cursorData":"000000000000000000000000000000000000000000000000000000000000000000000000000000","arrowData":"000000000000000000000000000000000000000000000000000000000000000000000000000000","slideText":"","autoDrop":true,"advanceNext":true,"puyoPair":"BR"},{"fieldData":["0","0","0","0","0","0","0","0","0","0","0","0","0","0","0","0","0","0","0","0","G","B","0","0","0","0","R","R","0","0","0","R","G","G","Y","Y","R","R","B","G","Y","R","Y","Y","G","B","B","R","G","G","Y","G","Y","Y","G","Y","B","R","B","R","Y","B","R","B","Y","R","Y","B","R","B","Y","R","Y","B","R","B","Y","G"],"fieldOriginal":["0","0","0","0","0","0","0","0","0","0","0","0","0","0","0","0","0","0","0","0","G","B","0","0","0","0","R","R","0","0","0","R","G","G","Y","Y","R","R","B","G","Y","R","Y","Y","G","B","B","R","G","G","Y","G","Y","Y","G","Y","B","R","B","R","Y","B","R","B","Y","R","Y","B","R","B","Y","R","Y","B","R","B","Y","G"],"shadowData":["0","0","0","0","0","0","0","0","0","0","0","0","0","0","0","0","0","0","0","R","G","B","0","G","0","R","R","R","0","G","0","R","G","G","Y","Y","R","R","B","G","Y","R","Y","Y","G","B","B","R","G","G","Y","G","Y","Y","G","Y","B","R","B","R","Y","B","R","B","Y","R","Y","B","R","B","Y","R","Y","B","R","B","Y","G"],"cursorData":"000000000000000000000000000000000000000000000000000000000000000000000000000000","arrowData":"000000000000000000000000000000000000000000000000000000000000000000000000000000","slideText":"","autoDrop":true,"advanceNext":true,"puyoPair":"GG"},{"fieldData":["0","0","0","0","0","0","0","0","0","0","0","0","0","0","0","0","0","0","0","0","G","B","0","G","0","0","R","R","0","G","0","R","G","G","Y","Y","R","R","B","G","Y","R","Y","Y","G","B","B","R","G","G","Y","G","Y","Y","G","Y","B","R","B","R","Y","B","R","B","Y","R","Y","B","R","B","Y","R","Y","B","R","B","Y","G"],"fieldOriginal":["0","0","0","0","0","0","0","0","0","0","0","0","0","0","0","0","0","0","0","0","G","B","0","G","0","0","R","R","0","G","0","R","G","G","Y","Y","R","R","B","G","Y","R","Y","Y","G","B","B","R","G","G","Y","G","Y","Y","G","Y","B","R","B","R","Y","B","R","B","Y","R","Y","B","R","B","Y","R","Y","B","R","B","Y","G"],"shadowData":["0","0","0","0","0","0","0","0","0","0","0","0","0","0","0","0","0","0","0","R","G","B","0","G","0","R","R","R","0","G","0","R","G","G","Y","Y","R","R","B","G","Y","R","Y","Y","G","B","B","R","G","G","Y","G","Y","Y","G","Y","B","R","B","R","Y","B","R","B","Y","R","Y","B","R","B","Y","R","Y","B","R","B","Y","G"],"cursorData":"000000000000000000000000000000000000000000000000000000000000000000000000000000","arrowData":"000000000000000000000000000000000000000000000000000000000000000000000000000000","slideText":"","autoDrop":true,"advanceNext":true,"puyoPair":"RR"},{"fieldData":["0","0","0","0","0","0","0","0","0","0","0","0","0","0","0","0","0","0","0","R","G","B","0","G","0","R","R","R","0","G","0","R","G","G","Y","Y","R","R","B","G","Y","R","Y","Y","G","B","B","R","G","G","Y","G","Y","Y","G","Y","B","R","B","R","Y","B","R","B","Y","R","Y","B","R","B","Y","R","Y","B","R","B","Y","G"],"fieldOriginal":["0","0","0","0","0","0","0","0","0","0","0","0","0","0","0","0","0","0","0","R","G","B","0","G","0","R","R","R","0","G","0","R","G","G","Y","Y","R","R","B","G","Y","R","Y","Y","G","B","B","R","G","G","Y","G","Y","Y","G","Y","B","R","B","R","Y","B","R","B","Y","R","Y","B","R","B","Y","R","Y","B","R","B","Y","G"],"shadowData":"000000000000000000000000000000000000000000000000000000000000000000000000000000","cursorData":"000000000000000000000000000000000000000000000000000000000000000000000000000000","arrowData":"000000000000000000000000000000000000000000000000000000000000000000000000000000","slideText":"","autoDrop":true,"advanceNext":true}],"next":{"seed":19217,"nextQueue":"YYBBRBBYYBYRGRYRYRBRYBYBBBBYGGRGGYBYYYYBGBRBYYYRRRGGGBRGYRBRGGRR"}}